<annotation>
    <folder>0</folder>
    <filename>00859.jpg</filename>
    <size>
        <width>425</width>
        <height>425</height>
        <depth>3</depth>
    </size>
    <segmented>0</segmented>
    <object>
        <name>chairs</name>
        <pose>Unspecified</pose>
        <truncated>0</truncated>
        <occluded>0</occluded>
        <difficult>0</difficult>
        <bndbox>
            <xmin>54</xmin>
            <ymin>19</ymin>
            <xmax>360</xmax>
            <ymax>399</ymax>
        </bndbox>
    </object>
</annotation>