<annotation>
    <folder>0</folder>
    <filename>00872.jpg</filename>
    <size>
        <width>1034</width>
        <height>1500</height>
        <depth>3</depth>
    </size>
    <segmented>0</segmented>
    <object>
        <name>chairs</name>
        <pose>Unspecified</pose>
        <truncated>0</truncated>
        <occluded>0</occluded>
        <difficult>0</difficult>
        <bndbox>
            <xmin>44</xmin>
            <ymin>52</ymin>
            <xmax>993</xmax>
            <ymax>1435</ymax>
        </bndbox>
    </object>
</annotation>