<annotation>
    <folder>0</folder>
    <filename>00999.jpg</filename>
    <size>
        <width>500</width>
        <height>500</height>
        <depth>3</depth>
    </size>
    <segmented>0</segmented>
    <object>
        <name>chairs</name>
        <pose>Unspecified</pose>
        <truncated>0</truncated>
        <occluded>0</occluded>
        <difficult>0</difficult>
        <bndbox>
            <xmin>110</xmin>
            <ymin>45</ymin>
            <xmax>382</xmax>
            <ymax>460</ymax>
        </bndbox>
    </object>
</annotation>