<annotation>
	<folder>downloads</folder>
	<filename>yoga589.png</filename>
	<path>/Users/chenweijia/yogaball/downloads/yoga589.png</path>
	<source>
		<database>Unknown</database>
	</source>
	<size>
		<width>1920</width>
		<height>1080</height>
		<depth>3</depth>
	</size>
	<segmented>0</segmented>
	<object>
		<name>yogaball</name>
		<pose>Unspecified</pose>
		<truncated>0</truncated>
		<difficult>0</difficult>
		<bndbox>
			<xmin>827</xmin>
			<ymin>611</ymin>
			<xmax>1214</xmax>
			<ymax>951</ymax>
		</bndbox>
	</object>
</annotation>
