<annotation>
    <folder>0</folder>
    <filename>00294.jpg</filename>
    <size>
        <width>1440</width>
        <height>1440</height>
        <depth>3</depth>
    </size>
    <segmented>0</segmented>
    <object>
        <name>chairs</name>
        <pose>Unspecified</pose>
        <truncated>0</truncated>
        <occluded>0</occluded>
        <difficult>0</difficult>
        <bndbox>
            <xmin>167</xmin>
            <ymin>52</ymin>
            <xmax>1260</xmax>
            <ymax>1395</ymax>
        </bndbox>
    </object>
</annotation>