<annotation>
    <folder>0</folder>
    <filename>00559.jpg</filename>
    <size>
        <width>1500</width>
        <height>1500</height>
        <depth>3</depth>
    </size>
    <segmented>0</segmented>
    <object>
        <name>chairs</name>
        <pose>Unspecified</pose>
        <truncated>0</truncated>
        <occluded>0</occluded>
        <difficult>0</difficult>
        <bndbox>
            <xmin>181</xmin>
            <ymin>99</ymin>
            <xmax>1309</xmax>
            <ymax>1409</ymax>
        </bndbox>
    </object>
</annotation>